Rdom/__init__.py
Rdom-0.1.dist-info/LICENSE
Rdom-0.1.dist-info/METADATA
Rdom-0.1.dist-info/WHEEL
Rdom-0.1.dist-info/top_level.txt
Rdom-0.1.dist-info/RECORD
