Metadata-Version: 2.1
Name: Rdom
Version: 0.1
Summary: A collection of random projects in Python.
Home-page: https://github.com/Yassperx/Rdom
Author: Yassperx
License: UNKNOWN
Platform: UNKNOWN
Classifier: Programming Language :: Python :: 3
Classifier: License :: OSI Approved :: MIT License
Classifier: Operating System :: OS Independent
Requires-Python: >=3.6
Requires-Dist: numpy
Requires-Dist: matplotlib
Requires-Dist: sklearn
Requires-Dist: tqdm
